MANIFEST.in
README.txt
plonetheme.p2-configure.zcml
setup.cfg
setup.py
docs/.DS_Store
docs/HISTORY.txt
docs/INSTALL.txt
docs/LICENSE.txt
docs/screenshot.jpg
plonetheme/.DS_Store
plonetheme/__init__.py
plonetheme.p2.egg-info/PKG-INFO
plonetheme.p2.egg-info/SOURCES.txt
plonetheme.p2.egg-info/dependency_links.txt
plonetheme.p2.egg-info/entry_points.txt
plonetheme.p2.egg-info/namespace_packages.txt
plonetheme.p2.egg-info/not-zip-safe
plonetheme.p2.egg-info/paster_plugins.txt
plonetheme.p2.egg-info/requires.txt
plonetheme.p2.egg-info/top_level.txt
plonetheme/p2/.DS_Store
plonetheme/p2/__init__.py
plonetheme/p2/configure.zcml
plonetheme/p2/profiles.zcml
plonetheme/p2/setuphandlers.py
plonetheme/p2/skins.zcml
plonetheme/p2/tests.py
plonetheme/p2/version.txt
plonetheme/p2/Extensions/Install.py
plonetheme/p2/Extensions/__init__.py
plonetheme/p2/browser/__init__.py
plonetheme/p2/browser/configure.zcml
plonetheme/p2/browser/footer.pt
plonetheme/p2/browser/interfaces.py
plonetheme/p2/browser/viewlet.pt
plonetheme/p2/browser/viewlets.py
plonetheme/p2/browser/images/README.txt
plonetheme/p2/browser/stylesheets/README.txt
plonetheme/p2/browser/stylesheets/main.css
plonetheme/p2/profiles/.DS_Store
plonetheme/p2/profiles/default/cssregistry.xml
plonetheme/p2/profiles/default/import_steps.xml
plonetheme/p2/profiles/default/jsregistry.xml
plonetheme/p2/profiles/default/metadata.xml
plonetheme/p2/profiles/default/plonetheme.p2_various.txt
plonetheme/p2/profiles/default/skins.xml
plonetheme/p2/profiles/default/viewlets.xml
plonetheme/p2/profiles/uninstall/cssregistry.xml
plonetheme/p2/profiles/uninstall/skins.xml
plonetheme/p2/profiles/uninstall/viewlets.xml
plonetheme/p2/skins/plonetheme_p2_custom_images/CONTENT.txt
plonetheme/p2/skins/plonetheme_p2_custom_templates/CONTENT.txt
plonetheme/p2/skins/plonetheme_p2_styles/CONTENT.txt
plonetheme/p2/skins/plonetheme_p2_styles/base_properties.props