Metadata-Version: 1.0
Name: plonetheme.p2
Version: 0.3.1bdev
Summary: An installable theme for Plone 3.0
Home-page: http://www.agapow.net/software/plonetheme.p2
Author: Paul-Michael Agapow
Author-email: agapow@bbsrc.ac.uk
License: BSD
Keywords: web zope plone theme
Platform: UNKNOWN
Classifier: Framework :: Plone
Classifier: Programming Language :: Python
Classifier: Topic :: Software Development :: Libraries :: Python Modules
